py_ce_forms_api/__init__.py
py_ce_forms_api/client.py
py_ce_forms_api/accounts/__init__.py
py_ce_forms_api/accounts/accounts.py
py_ce_forms_api/api/__init__.py
py_ce_forms_api/api/bearer_auth.py
py_ce_forms_api/api/client.py
py_ce_forms_api/api/exceptions.py
py_ce_forms_api/api/modules.py
py_ce_forms_api/assets/__init__.py
py_ce_forms_api/assets/asset_elt.py
py_ce_forms_api/assets/asset_local_file_elt.py
py_ce_forms_api/assets/assets.py
py_ce_forms_api/cli/__init__.py
py_ce_forms_api/cli/form_info.py
py_ce_forms_api/cli/py_ce_forms.py
py_ce_forms_api/core/__init__.py
py_ce_forms_api/core/form_core.py
py_ce_forms_api/form/__init__.py
py_ce_forms_api/form/form.py
py_ce_forms_api/form/form_block.py
py_ce_forms_api/form/form_block_asset_array.py
py_ce_forms_api/form/form_block_assoc.py
py_ce_forms_api/form/form_block_factory.py
py_ce_forms_api/form/form_utils.py
py_ce_forms_api/forms/__init__.py
py_ce_forms_api/forms/forms.py
py_ce_forms_api/io/__init__.py
py_ce_forms_api/io/json_dump.py
py_ce_forms_api/old_project/__init__.py
py_ce_forms_api/old_project/old_project.py
py_ce_forms_api/old_project/old_project_block.py
py_ce_forms_api/old_projects/__init__.py
py_ce_forms_api/old_projects/old_projects.py
py_ce_forms_api/processing/__init__.py
py_ce_forms_api/processing/processing.py
py_ce_forms_api/processing/processing_tasks.py
py_ce_forms_api/processing/task.py
py_ce_forms_api/processing/task_pool.py
py_ce_forms_api/processing_client/__init__.py
py_ce_forms_api/processing_client/processing_client.py
py_ce_forms_api/projects/__init__.py
py_ce_forms_api/projects/project.py
py_ce_forms_api/projects/projects.py
py_ce_forms_api/query/__init__.py
py_ce_forms_api/query/form_mutate.py
py_ce_forms_api/query/forms_query.py
py_ce_forms_api/query/forms_query_array.py
py_ce_forms_api/query/forms_res.py
py_ce_forms_api/query/forms_res_iterable.py
py_ce_forms_api/root/__init__.py
py_ce_forms_api/root/root.py
py_ce_forms_api/roots/__init__.py
py_ce_forms_api/roots/roots.py
py_ce_forms_api-0.1.15.dist-info/LICENSE
py_ce_forms_api-0.1.15.dist-info/METADATA
py_ce_forms_api-0.1.15.dist-info/WHEEL
py_ce_forms_api-0.1.15.dist-info/entry_points.txt
py_ce_forms_api-0.1.15.dist-info/top_level.txt
py_ce_forms_api-0.1.15.dist-info/RECORD
